[
  {
    "scheme_name":"Pradhan Mantri Kisan Samman Nidhi (PM-KISAN)",
    "launch_date":"2018-12-01",
    "objective":"Direct income support to small & marginal farmers",
    "benefit_amount":6000,
    "benefit_unit":"INR/year",
    "benefit_frequency":"3 installments",
    "eligibility_crops":"all",
    "eligibility_land_holding":null,
    "eligibility_region":"All India",
    "risk_covered":null,
    "approach_authority":"District Agriculture Office / Patwari",
    "application_channel":"PM-KISAN portal, CSC",
    "category":"income_support",
    "text_features":"direct income support small marginal farmers"
  },
  {
    "scheme_name":"Pradhan Mantri Fasal Bima Yojana (PMFBY)",
    "launch_date":"2016-02-18",
    "objective":"Comprehensive crop insurance against natural calamities",
    "benefit_amount":null,
    "benefit_unit":"% premium subsidy",
    "benefit_frequency":"annual",
    "eligibility_crops":"food, oilseed, commercial, horticultural",
    "eligibility_land_holding":null,
    "eligibility_region":"All India",
    "risk_covered":"drought,flood,cyclone,pests,diseases,postharvest",
    "approach_authority":"Insurance Co (via bank branch)",
    "application_channel":"PMFBY portal, KCC-linked",
    "category":"insurance",
    "text_features":"crop insurance natural calamities pests diseases"
  },
  {
    "scheme_name":"Pradhan Mantri Krishi Sinchayee Yojana (PMKSY)",
    "launch_date":"2015-07-01",
    "objective":"Ensure irrigation for every field and efficient water use",
    "benefit_amount":null,
    "benefit_unit":"subsidy on irrigation infrastructure",
    "benefit_frequency":"project-based",
    "eligibility_crops":"all",
    "eligibility_land_holding":2,
    "eligibility_region":"All India",
    "risk_covered":null,
    "approach_authority":"District Irrigation Dept",
    "application_channel":"PMKSY portal",
    "category":"irrigation",
    "text_features":"financial assistance irrigation micro irrigation water efficiency"
  },
  {
    "scheme_name":"Kisan Credit Card (KCC)",
    "launch_date":"1998-08-15",
    "objective":"Affordable credit for cultivation & investment",
    "benefit_amount":null,
    "benefit_unit":"4% interest subsidy",
    "benefit_frequency":"revolving credit",
    "eligibility_crops":"all",
    "eligibility_land_holding":null,
    "eligibility_region":"All India",
    "risk_covered":null,
    "approach_authority":"Participating bank branch",
    "application_channel":"Bank branch",
    "category":"credit",
    "text_features":"credit cultivation investment affordable credit"
  },
  {
    "scheme_name":"Soil Health Card Scheme",
    "launch_date":"2015-07-19",
    "objective":"Promote soil testing & nutrient management",
    "benefit_amount":null,
    "benefit_unit":"free soil test",
    "benefit_frequency":"once every 3 years",
    "eligibility_crops":"all",
    "eligibility_land_holding":null,
    "eligibility_region":"All India",
    "risk_covered":null,
    "approach_authority":"Agriculture Dept / KVK",
    "application_channel":"Krishi Vigyan Kendra",
    "category":"soil_health",
    "text_features":"soil testing nutrient recommendation soil health"
  },
  {
    "scheme_name":"Pradhan Mantri Kisan Maandhan Yojana (PM-KMY)",
    "launch_date":"2019-09-12",
    "objective":"Pension for small & marginal farmers",
    "benefit_amount":3000,
    "benefit_unit":"INR/month",
    "benefit_frequency":"monthly after 60 yrs",
    "eligibility_crops":"all",
    "eligibility_land_holding":2,
    "eligibility_region":"All India",
    "risk_covered":null,
    "approach_authority":"District Agriculture Office",
    "application_channel":"PM-KMY portal, CSC",
    "category":"pension",
    "text_features":"monthly pension farmers landholding up to two hectares"
  },
  {
    "scheme_name":"National Agriculture Market (e-NAM)",
    "launch_date":"2016-04-14",
    "objective":"Provide unified online market for farm produce",
    "benefit_amount":null,
    "benefit_unit":null,
    "benefit_frequency":null,
    "eligibility_crops":"all agri commodities",
    "eligibility_land_holding":null,
    "eligibility_region":"States with eNAM",
    "risk_covered":null,
    "approach_authority":"APMC Market Yard officials",
    "application_channel":"e-NAM portal",
    "category":"marketing",
    "text_features":"online trading better price unified market platform"
  },
  {
    "scheme_name":"Rashtriya Krishi Vikas Yojana (RKVY)",
    "launch_date":"2007-12-28",
    "objective":"Support state-level agri projects & innovation",
    "benefit_amount":null,
    "benefit_unit":"100% funding",
    "benefit_frequency":"plan-period",
    "eligibility_crops":"state prioritized",
    "eligibility_land_holding":null,
    "eligibility_region":"State governments",
    "risk_covered":null,
    "approach_authority":"State Agriculture Dept",
    "application_channel":"State RKVY portal",
    "category":"development",
    "text_features":"state agricultural development innovation infrastructure"
  },
  {
    "scheme_name":"Paramparagat Krishi Vikas Yojana (PKVY)",
    "launch_date":"2015-05-14",
    "objective":"Promote organic farming clusters",
    "benefit_amount":null,
    "benefit_unit":"funding for inputs + certification",
    "benefit_frequency":"project-based",
    "eligibility_crops":"organic clusters",
    "eligibility_land_holding":null,
    "eligibility_region":"Selected clusters",
    "risk_covered":null,
    "approach_authority":"State Agriculture Dept",
    "application_channel":"PKVY portal",
    "category":"organic_farming",
    "text_features":"organic farming certification cluster development"
  },
  {
    "scheme_name":"National Food Security Mission (NFSM)",
    "launch_date":"2007-02-10",
    "objective":"Increase production of rice, wheat, pulses, oilseeds",
    "benefit_amount":null,
    "benefit_unit":"subsidy for inputs",
    "benefit_frequency":"annual",
    "eligibility_crops":"rice,wheat,pulses,oilseeds",
    "eligibility_land_holding":null,
    "eligibility_region":"All India",
    "risk_covered":null,
    "approach_authority":"District Agril Officer",
    "application_channel":"NFSM portal",
    "category":"production",
    "text_features":"increase crop production input subsidy extension services"
  },
  {
    "scheme_name":"National Mission on Sustainable Agriculture (NMSA)",
    "launch_date":"2014-08-05",
    "objective":"Promote sustainable & climate-resilient agriculture",
    "benefit_amount":null,
    "benefit_unit":"support for practices",
    "benefit_frequency":null,
    "eligibility_crops":"all",
    "eligibility_land_holding":null,
    "eligibility_region":"All India",
    "risk_covered":null,
    "approach_authority":"Krishi Vigyan Kendra",
    "application_channel":"NMSA portal, KVK",
    "category":"sustainability",
    "text_features":"sustainable agriculture climate resilience water soil practices"
  },
  {
    "scheme_name":"Dairy Entrepreneurship Development Scheme (DEDS)",
    "launch_date":"2013-11-06",
    "objective":"Promote dairy infrastructure & units",
    "benefit_amount":null,
    "benefit_unit":"subsidy upto 50%",
    "benefit_frequency":"one-time",
    "eligibility_crops":"dairy",
    "eligibility_land_holding":null,
    "eligibility_region":"All India",
    "risk_covered":null,
    "approach_authority":"NABARD / Dairy Coop Societies",
    "application_channel":"DEDS portal",
    "category":"dairy",
    "text_features":"dairy farm processing cold storage subsidy entrepreneurship"
  },
  {
    "scheme_name":"Agri-Clinic & Agri-Business Centre Scheme",
    "launch_date":"2002-03-15",
    "objective":"Support agri-entrepreneurship",
    "benefit_amount":null,
    "benefit_unit":"subsidy upto 40%",
    "benefit_frequency":"one-time",
    "eligibility_crops":"value-added services",
    "eligibility_land_holding":null,
    "eligibility_region":"All India",
    "risk_covered":null,
    "approach_authority":"Project Implementing Agency / NABARD",
    "application_channel":"ACABC portal",
    "category":"agrientrepreneur",
    "text_features":"agri entrepreneurship clinics business centres subsidy"
  },
  {
    "scheme_name":"National Beekeeping & Honey Mission (NBHM)",
    "launch_date":"2020-08-20",
    "objective":"Promote beekeeping & honey production",
    "benefit_amount":null,
    "benefit_unit":"subsidy upto 60%",
    "benefit_frequency":"one-time",
    "eligibility_crops":"beekeeping",
    "eligibility_land_holding":null,
    "eligibility_region":"All India",
    "risk_covered":null,
    "approach_authority":"National Bee Board",
    "application_channel":"NBHM portal",
    "category":"beekeeping",
    "text_features":"beekeeping honey production training subsidy"
  },
  {
    "scheme_name":"Atal Bhujal Yojana",
    "launch_date":"2020-12-25",
    "objective":"Community groundwater management",
    "benefit_amount":null,
    "benefit_unit":"project grants",
    "benefit_frequency":"project-based",
    "eligibility_crops":"all",
    "eligibility_land_holding":null,
    "eligibility_region":"Priority districts",
    "risk_covered":null,
    "approach_authority":"Gram Panchayat",
    "application_channel":"ABHY programme",
    "category":"water_management",
    "text_features":"groundwater management community participation water conservation"
  },
  {
    "scheme_name":"Pradhan Mantri KUSUM",
    "launch_date":"2019-03-08",
    "objective":"Solar pumps & grid-connected solar plants",
    "benefit_amount":null,
    "benefit_unit":"60% subsidy",
    "benefit_frequency":"one-time",
    "eligibility_crops":"all",
    "eligibility_land_holding":null,
    "eligibility_region":"All India",
    "risk_covered":null,
    "approach_authority":"State Nodal Agency",
    "application_channel":"KUSUM portal",
    "category":"energy",
    "text_features":"solar pumps grid solar plants subsidy renewable energy"
  },
  {
    "scheme_name":"Gramin Bhandaran Yojana",
    "launch_date":"2001-04-01",
    "objective":"Subsidy for rural godown infrastructure",
    "benefit_amount":null,
    "benefit_unit":"25‑50% capex subsidy",
    "benefit_frequency":"one-time",
    "eligibility_crops":"storage units",
    "eligibility_land_holding":null,
    "eligibility_region":"All India",
    "risk_covered":null,
    "approach_authority":"DMI / NABARD",
    "application_channel":"GBY portal",
    "category":"storage",
    "text_features":"rural storage godown subsidy capacity enhancement"
  },
  {
    "scheme_name":"Operation Greens",
    "launch_date":"2018-11-05",
    "objective":"Stabilise prices of tomato, onion, potato",
    "benefit_amount":500,
    "benefit_unit":"crore fund",
    "benefit_frequency":"annual",
    "eligibility_crops":"tomato,onion,potato",
    "eligibility_land_holding":null,
    "eligibility_region":"All India",
    "risk_covered":null,
    "approach_authority":"Ministry of Food Processing Industries",
    "application_channel":"OG portal",
    "category":"price_stabilization",
    "text_features":"tomato onion potato market logistics stability"
  },
  {
    "scheme_name":"Rythu Bandhu Scheme",
    "launch_date":"2018-05-10",
    "objective":"Investment support for field crops (Telangana)",
    "benefit_amount":10000,
    "benefit_unit":"INR per acre per season",
    "benefit_frequency":"biannual",
    "eligibility_crops":"all field crops",
    "eligibility_land_holding":null,
    "eligibility_region":"Telangana",
    "risk_covered":null,
    "approach_authority":"District Collector Office",
    "application_channel":"RTB portal",
    "category":"investment_support",
    "text_features":"investment support Telangana farmers per acre per season"
  },
  {
    "scheme_name":"Pradhan Mantri Matsya Sampada Yojana",
    "launch_date":"2020-09-10",
    "objective":"Boost fisheries & aquaculture infrastructure",
    "benefit_amount":null,
    "benefit_unit":"subsidy on infrastructure",
    "benefit_frequency":"project-based",
    "eligibility_crops":"fisheries,aqua",
    "eligibility_land_holding":null,
    "eligibility_region":"All India",
    "risk_covered":null,
    "approach_authority":"State Fisheries Dept",
    "application_channel":"PMMSY portal",
    "category":"fisheries",
    "text_features":"fishery infrastructure aquaculture subsidy processing cold chain"
  }
]
